[
  {
    "id": "soP9m8MdKeQX_ZXZOCSaL",
    "companyId": "pVbRRBQtMVw6lUAkj1k43",
    "title": "Frontend Developer",
    "description": "We are looking for a Frontend Developer familiar with React."
  },
  {
    "id": "GR7vTA_btqTnLtXcEDX8C",
    "companyId": "pVbRRBQtMVw6lUAkj1k43",
    "title": "Backend Developer",
    "description": "We are looking for a Backend Developer familiar with Node.js and Express."
  },
  {
    "id": "yX71WsWqBRAFuMAIDj4W0",
    "companyId": "wvdB54Gqbdp_NZTXK9Tue",
    "title": "Full-Stack Developer",
    "description": "We are looking for a Full-Stack Developer familiar with Node.js, Express, and React."
  },
  {
    "id": "Vnxo56UGEt31qBMhxpfcI",
    "title": "job_test",
    "companyId": "pVbRRBQtMVw6lUAkj1k43",
    "description": "test"
  },
  {
    "id": "CtICnRzbdq1RDj00vD5rs",
    "title": "update test",
    "companyId": "pVbRRBQtMVw6lUAkj1k43",
    "description": "update test"
  },
  {
    "id": "tn_YmEdx_YxaOv-OQYfFg",
    "title": "test2",
    "companyId": "pVbRRBQtMVw6lUAkj1k43",
    "description": "wwww"
  },
  {
    "id": "E9Muw4Eg9pFjKVQsR_1pv",
    "title": "create test 1 with auth",
    "companyId": "pVbRRBQtMVw6lUAkj1k43",
    "description": "create test"
  },
  {
    "id": "SqOk-hmZHqukvskt4gmaI",
    "title": "create test with company asso user",
    "description": "create test company-user",
    "companyId": "pVbRRBQtMVw6lUAkj1k43"
  },
  {
    "id": "_Fh3EW5lSsovziQpqXkLz",
    "title": "zxxzxcxz",
    "description": "zxczxc",
    "companyId": "pVbRRBQtMVw6lUAkj1k43"
  },
  {
    "id": "F23MV8nzfQ_2_5kJudx-d",
    "title": "dddddd",
    "description": "dd",
    "companyId": "pVbRRBQtMVw6lUAkj1k43"
  },
  {
    "id": "_bMh-ZsThBLrfN7MG-tH8",
    "title": "wweeqeqe",
    "description": "weqeqeq",
    "companyId": "pVbRRBQtMVw6lUAkj1k43"
  }
]